{
  "authorizationReversalAmount": -93661319,
  "paymentGatewayDate": "00:01:01",
  "paymentGatewayReferenceNumber": "sed laboris laborum esse",
  "id": "reprehenderit occaecat non labore in",
  "paymentAuthorizationProcessingMode": "magna ut sint",
  "paymentGatewayResult": [
    {
      "id": "ad sunt Ut laboris",
      "name": "voluptate enim dolore ullamco in",
      "description": "dolor"
    },
    {
      "id": "eiusmod occaecat",
      "name": "ea Duis",
      "description": "fugiat enim"
    },
    {
      "id": "nulla",
      "name": "esse nisi aliqua",
      "description": "adipisicing do amet in"
    },
    {
      "id": "anim velit Excepteur",
      "name": "enim magna eiusmod Excepteur",
      "description": "in consequat dolore magna"
    },
    {
      "id": "incididunt id minim dolor",
      "name": "est Duis consectetur nisi",
      "description": "do est sint proident Duis"
    },
    {
      "id": "dolore est",
      "name": "ut",
      "description": "consectetur do incididunt"
    },
    {
      "id": "in irure anim eu",
      "name": "anim cillum proident",
      "description": "pariatur magna occaecat non"
    },
    {
      "id": "minim",
      "name": "laborum est culpa",
      "description": "dolor Excepteur veniam sunt velit"
    },
    {
      "id": "voluptate sit",
      "name": "mollit sunt sit irure nulla",
      "description": "ea"
    },
    {
      "id": "velit ut sint pariatur nisi",
      "name": "ipsum veniam",
      "description": "sed dolor esse"
    },
    {
      "id": "fugiat non sunt cillum",
      "name": "veniam Lorem ut deserunt",
      "description": "quis ut occaecat est cupidatat"
    },
    {
      "id": "laborum",
      "name": "nisi officia magna proident",
      "description": "ex"
    },
    {
      "id": "sed deserunt",
      "name": "dolor",
      "description": "fugiat ut culpa nulla"
    },
    {
      "id": "magna officia laboris",
      "name": "voluptate enim cupidatat labore",
      "description": "aliquip officia eu id"
    },
    {
      "id": "ut ea id dolore",
      "name": "ad et veniam Ut fugiat",
      "description": "do ex"
    },
    {
      "id": "pariatur ut",
      "name": "eiusmod anim veniam",
      "description": "aute non sed"
    },
    {
      "id": "pariatur qui Excepteur",
      "name": "do exercitation",
      "description": "nostrud sit consequat eiusmod exercitation"
    },
    {
      "id": "dolore non dolore",
      "name": "labore nisi consequat cillum deserunt",
      "description": "eiusmod reprehenderit mollit deserunt"
    },
    {
      "id": "id est",
      "name": "elit esse",
      "description": "cillum"
    },
    {
      "id": "culpa voluptate eiusmod minim",
      "name": "Lorem ullamco",
      "description": "amet eiusmod laborum ut"
    },
    {
      "id": "voluptate",
      "name": "exercitation qui sed",
      "description": "fugiat"
    },
    {
      "id": "incididunt aliquip eiusmod",
      "name": "cillum",
      "description": "reprehenderit laboris commodo Excepteur eiusmod"
    },
    {
      "id": "Duis ipsum laboris ut",
      "name": "reprehenderit ex sint proident",
      "description": "ex et irure laborum occaecat"
    },
    {
      "id": "occaecat ipsum veniam elit",
      "name": "est aliqua id reprehenderit",
      "description": "est Excepteur cillum"
    },
    {
      "id": "ex fugiat",
      "name": "veniam velit cupidatat anim",
      "description": "in aliqua"
    },
    {
      "id": "ad aliquip Excepteur ex",
      "name": "adipisicing tempor cillum",
      "description": "quis occaecat non"
    },
    {
      "id": "ullamco magna",
      "name": "deserunt",
      "description": "fugiat nostrud laborum anim et"
    },
    {
      "id": "fugiat incididunt",
      "name": "sed consequat aliquip et",
      "description": "eu"
    },
    {
      "id": "sit eu cillum voluptate in",
      "name": "voluptate",
      "description": "enim esse velit fugiat pariatur"
    },
    {
      "id": "minim",
      "name": "officia Excepteur consectetur in",
      "description": "dolor"
    },
    {
      "id": "elit amet laborum laboris",
      "name": "nostrud sint sit",
      "description": "exercitation"
    },
    {
      "id": "veniam ex adipisicing et",
      "name": "ullamco",
      "description": "magna est Lorem"
    },
    {
      "id": "in",
      "name": "voluptate",
      "description": "dolore nostrud"
    },
    {
      "id": "Ut amet sint",
      "name": "in",
      "description": "et magna cillum tempor esse"
    },
    {
      "id": "consectetur voluptate Ut laboris",
      "name": "laborum est dolore cillum sit",
      "description": "eiusmod in"
    },
    {
      "id": "nostrud anim",
      "name": "tempor aute qui sint sed",
      "description": "dolor in aliqua ea"
    },
    {
      "id": "aliqua",
      "name": "Excepteur reprehenderit",
      "description": "nisi esse anim ea sint"
    },
    {
      "id": "adipisicing ex nisi",
      "name": "est reprehenderit",
      "description": "nostrud"
    },
    {
      "id": "nulla magna in",
      "name": "Ut",
      "description": "incididunt pariatur nostrud in"
    },
    {
      "id": "fugiat laborum",
      "name": "minim reprehenderit",
      "description": "sint qui"
    },
    {
      "id": "consectetur id",
      "name": "culpa eu Duis laboris",
      "description": "irure laborum nostrud voluptate"
    },
    {
      "id": "dolore laborum ut Excepteur",
      "name": "Excepteur ullamco Lorem Ut ut",
      "description": "pariatur"
    },
    {
      "id": "culpa",
      "name": "magna",
      "description": "enim"
    },
    {
      "id": "ipsum est",
      "name": "consectetur in laboris",
      "description": "veniam enim"
    },
    {
      "id": "irure aliqua",
      "name": "consectetur magna in exercitation",
      "description": "quis velit"
    },
    {
      "id": "elit Duis",
      "name": "nisi Duis est in",
      "description": "amet minim occaecat officia"
    }
  ],
  "paymentAuthorizationReversalStatus": "ad est dolore",
  "requestDate": "00:01:01",
  "externalCreatedDate": "2018-10-17",
  "capturePayment": [
    "adipisicing",
    "culpa est",
    "cillum qui",
    "deserunt eiusmod",
    "aliqua Excepteur",
    "ad consectetur labore laborum",
    "quis officia",
    "sunt dolore magna eiusmod culpa",
    "incididunt",
    "pariatur reprehenderit voluptate consequat id",
    "eu in",
    "laborum id eu Duis minim",
    "Duis",
    "irure esse Excepteur ut",
    "Duis culpa ipsum",
    "ut officia do",
    "ullamco in exercitation do",
    "esse Ut",
    "dolor irure sed",
    "ea adipisicing ad labore",
    "eu",
    "in eiusmod veniam aute non",
    "laboris elit nulla esse",
    "irure",
    "mollit laboris",
    "sint et elit",
    "nisi",
    "Excepteur labore reprehenderit",
    "culpa tempor in in",
    "minim eu",
    "qui aliqua"
  ],
  "paymentAuthorizationReversalName": "consequat",
  "iPAddress": "aliquip in culpa non",
  "paymentAuthorizationReversalCommentText": "deserunt",
  "macAddress": "nostrud sed sunt non",
  "paymentGatewayInternalReferenceNumber": "in in nulla do",
  "customerAuthorizationReversalPhone": "exercitation amet in sunt incididunt",
  "auditDetail": {
    "createdOn": "1976-01-02T07:43:12.443Z",
    "createdBy": "fugiat velit ex",
    "updatedOn": "1947-03-11T18:05:00.326Z",
    "updatedBy": "consequat incididunt cupidatat",
    "isDeleted": false
  }
}
